nost_tools/__init__.py
nost_tools/application.py
nost_tools/application_utils.py
nost_tools/configuration.py
nost_tools/entity.py
nost_tools/errors.py
nost_tools/logger_application.py
nost_tools/managed_application.py
nost_tools/manager.py
nost_tools/observer.py
nost_tools/publisher.py
nost_tools/schemas.py
nost_tools/simulator.py
nost_tools-3.0.6.dist-info/licenses/LICENSE
nost_tools-3.0.6.dist-info/METADATA
nost_tools-3.0.6.dist-info/WHEEL
nost_tools-3.0.6.dist-info/top_level.txt
nost_tools-3.0.6.dist-info/RECORD
