Metadata-Version: 2.4
Name: nost_tools
Version: 3.0.6
Summary: Tools for Novel Observing Strategies Testbed (NOS-T) Applications
Author-email: "Paul T. Grogan" <paul.grogan@asu.edu>, "Emmanuel M. Gonzalez" <emmanuelgonzalez@asu.edu>
License-Expression: BSD-3-Clause
Classifier: Programming Language :: Python :: 3
Classifier: Operating System :: OS Independent
Classifier: Development Status :: 4 - Beta
Requires-Python: >=3.9
License-File: LICENSE
Requires-Dist: ntplib
Requires-Dist: numpy>=2
Requires-Dist: pandas>=2
Requires-Dist: pydantic<3,>=2
Requires-Dist: python-dateutil
Requires-Dist: pika>=1
Requires-Dist: python-dotenv
Requires-Dist: pyyaml
Requires-Dist: python-keycloak>=5
Provides-Extra: dev
Requires-Dist: black[jupyter]>=24.2; extra == "dev"
Requires-Dist: coverage; extra == "dev"
Requires-Dist: pylint; extra == "dev"
Requires-Dist: pylint-pydantic; extra == "dev"
Requires-Dist: pytest; extra == "dev"
Provides-Extra: examples
Requires-Dist: dash; extra == "examples"
Requires-Dist: dash-daq; extra == "examples"
Requires-Dist: flask; extra == "examples"
Requires-Dist: scipy; extra == "examples"
Requires-Dist: seaborn; extra == "examples"
Requires-Dist: skyfield; extra == "examples"
Requires-Dist: matplotlib>=3; extra == "examples"
Requires-Dist: xarray>=2023; extra == "examples"
Requires-Dist: rioxarray>=0.13; extra == "examples"
Requires-Dist: geopandas>=0.12; extra == "examples"
Requires-Dist: netCDF4>=1.6; extra == "examples"
Requires-Dist: aiobotocore>=2.17; extra == "examples"
Requires-Dist: botocore>=1.35; extra == "examples"
Requires-Dist: boto3>=1.35; extra == "examples"
Requires-Dist: tatc<=3.4.3; extra == "examples"
Requires-Dist: s3fs>=2024.10.0; extra == "examples"
Requires-Dist: pulp>=2.9.0; extra == "examples"
Requires-Dist: h5netcdf>=1.0; extra == "examples"
Provides-Extra: docs
Requires-Dist: autodoc_pydantic>=2; extra == "docs"
Requires-Dist: docutils; extra == "docs"
Requires-Dist: readthedocs-sphinx-search; extra == "docs"
Requires-Dist: sphinx>=7; extra == "docs"
Requires-Dist: sphinx_rtd_theme; extra == "docs"
Requires-Dist: sphinx-copybutton; extra == "docs"
Requires-Dist: sphinx_design; extra == "docs"
Requires-Dist: myst-parser; extra == "docs"
Requires-Dist: sphinxcontrib-mermaid; extra == "docs"
Dynamic: license-file
